nirfmxlte/__init__.py
nirfmxlte/acp.py
nirfmxlte/acp_component_carrier_results.py
nirfmxlte/acp_configuration.py
nirfmxlte/acp_results.py
nirfmxlte/attributes.py
nirfmxlte/chp.py
nirfmxlte/chp_component_carrier_results.py
nirfmxlte/chp_configuration.py
nirfmxlte/chp_results.py
nirfmxlte/component_carrier.py
nirfmxlte/enums.py
nirfmxlte/errors.py
nirfmxlte/examples/nirfmxlte_acp_single_carrier.py
nirfmxlte/examples/nirfmxlte_chp_single_carrier.py
nirfmxlte/examples/nirfmxlte_sem_single_carrier.py
nirfmxlte/examples/nirfmxlte_ul_modacc_single_carrier.py
nirfmxlte/examples/nirfmxlte_ul_pvt_single_carrier_grpc.py
nirfmxlte/grpc_session_options.py
nirfmxlte/internal/_custom_types.py
nirfmxlte/internal/_grpc_stub_interpreter.py
nirfmxlte/internal/_helper.py
nirfmxlte/internal/_library.py
nirfmxlte/internal/_library_interpreter.py
nirfmxlte/internal/_library_singleton.py
nirfmxlte/internal/nidevice_pb2.py
nirfmxlte/internal/nidevice_pb2_grpc.py
nirfmxlte/internal/nirfmxlte_pb2.py
nirfmxlte/internal/nirfmxlte_pb2_grpc.py
nirfmxlte/internal/session_pb2.py
nirfmxlte/internal/session_pb2_grpc.py
nirfmxlte/lte.py
nirfmxlte/modacc.py
nirfmxlte/modacc_configuration.py
nirfmxlte/modacc_results.py
nirfmxlte/obw.py
nirfmxlte/obw_configuration.py
nirfmxlte/obw_results.py
nirfmxlte/pvt.py
nirfmxlte/pvt_configuration.py
nirfmxlte/pvt_results.py
nirfmxlte/sem.py
nirfmxlte/sem_component_carrier_configuration.py
nirfmxlte/sem_component_carrier_results.py
nirfmxlte/sem_configuration.py
nirfmxlte/sem_results.py
nirfmxlte/slotphase.py
nirfmxlte/slotphase_configuration.py
nirfmxlte/slotphase_results.py
nirfmxlte/slotpower.py
nirfmxlte/slotpower_configuration.py
nirfmxlte/slotpower_results.py
nirfmxlte/txp.py
nirfmxlte/txp_configuration.py
nirfmxlte/txp_results.py
nirfmxlte-26.0.0.dist-info/licenses/LICENSE
nirfmxlte-26.0.0.dist-info/METADATA
nirfmxlte-26.0.0.dist-info/WHEEL
nirfmxlte-26.0.0.dist-info/RECORD
